iuye_utils/__init__.py
iuye_utils/account_utils.py
iuye_utils/config_utils.py
iuye_utils/date_utils.py
iuye_utils/db_utils.py
iuye_utils/file_utils.py
iuye_utils/helper.py
iuye_utils/mongo_utils.py
iuye_utils/open_resource_manager.py
iuye_utils/pdf_utils.py
iuye_utils/rabbitmq_utils.py
iuye_utils/redis_data_manager.py
iuye_utils/redis_utils.py
iuye_utils/request_utils.py
iuye_utils/trade_date_utils.py
iuye_utils/trade_time_utils.py
iuye_utils/trade_utils.py
iuye_common-0.0.1.dev7.dist-info/LICENSE
iuye_common-0.0.1.dev7.dist-info/METADATA
iuye_common-0.0.1.dev7.dist-info/WHEEL
iuye_common-0.0.1.dev7.dist-info/top_level.txt
iuye_common-0.0.1.dev7.dist-info/RECORD
