Metadata-Version: 2.1
Name: iuye-common
Version: 0.0.1.dev7
Summary: iuye common
Home-page: https://gitee.com/iuye/iuye_common
Author: Jerold Liu
Author-email: bymlyong@163.com
License: UNKNOWN
Platform: UNKNOWN
Classifier: Programming Language :: Python :: 3
Classifier: License :: OSI Approved :: MIT License
Classifier: Operating System :: OS Independent
Requires-Python: >=3.6
License-File: LICENSE
Requires-Dist: pandas
Requires-Dist: requests
Requires-Dist: urllib3
